{
  "schema_version": 1,
  "page": {
    "id": "loadout-presets",
    "title": "配装预设",
    "source_files": [
      "frontend/src/components/PatchTool.vue",
      "frontend/src/components/LoadoutViewer.vue",
      "frontend/src/components/LoadoutEditor.vue"
    ],
    "layout": "浏览态的共享工具舞台为左侧约 62% 的存档、角色与十五个预设槽功能区、右侧约 38% 的独立透明立绘轨，角色气泡随立绘位于右侧；立绘不得侵入浏览存档、目标槽、导入导出或写入入口。点击编辑后，原页面被无立绘的全宽专用编辑工作区替换；窗口宽度不超过 900px 时浏览态也隐藏立绘轨并改为单栏。"
  },
  "functionality": {
    "user_goal": "在游戏完全退出后查看并安全编辑存档中的角色配装预设，必要时克隆、清空、导入或导出单份配装。",
    "capabilities": [
      "选择存档槽或浏览存档文件，查看每名角色的十五个预设槽",
      "编辑武器、十二个因子、四个主动技能与最多五十项专精，或克隆和清空目标槽",
      "导入导出单份配装，并可选择同步更新四个全局召唤槽",
      "写入前创建备份并在写入后重新载入校验"
    ],
    "workflow": [
      "完全退出游戏，选择正确存档槽或浏览到目标存档",
      "选择角色与十五个预设槽之一，检查已有内容后编辑、克隆、清空或导入",
      "确认是否更新共享的四个召唤槽，点击备份并写入，再重新载入核对字段"
    ],
    "primary_action": "在确认角色和目标预设槽后，把一整份武器、因子、技能与专精配置备份并写入存档。",
    "primary_risk": "选错角色或已占用的目标槽会覆盖既有配装；启用全局召唤更新还会改动所有角色共享的四个召唤槽。",
    "success_state": "工具先生成可恢复的备份，再写入目标槽并重新载入，显示武器、十二因子、四技能、专精与可选召唤字段一致。",
    "ui_copy": "先备份，再确认角色和目标槽；已有配装会被覆盖。"
  },
  "portrait": {
    "character": "gran",
    "selection_reason": "以 portable roster 的官方 gran.png 为身份锚点；格兰作为可靠的队长，适合表达在写档前统筹并复核一整份配装。",
    "action": "格兰正面偏三分之二站立，把唯一一本半合拢的深蓝金备份配装册横抱在胸前；册页边缘只露出恰好四枚宽大、无文字且轮廓各异的分类页签，左前臂承担书册重量，右手拉紧穿过书脊的唯一封缄带并扣合唯一实体封印，视线落在封印接触点，神情沉着负责。",
    "prop": "一本半合拢的深蓝金备份配装册，带有四枚宽大无文字分类页签、一条封缄带和一个实体封印。",
    "gameplay_references": [
      {
        "file": "D:/gbf/.worktrees/loadout-fullscreen/frontend/public/loadout-icons/weapons/cmn_imgequ_wp0000.png",
        "subject": "Traveller's Sword (Gran) / WEP_PL0000_01_01",
        "use": "仅约束武器的准确几何；武器保持入鞘并与配装册完全分离"
      }
    ],
    "physical_rules": [
      "书册只能露出四枚宽大分类页签，页签不得出现文字、数字、图标或细密槽位；精确的十二因子、四技能和专精数量只由真实 UI 展示",
      "左前臂把半合拢书册抱在胸前并承担重量，右手只拉紧一条封缄带并扣合唯一封印，双眼朝向封印而非观众外侧",
      "棕色乱发、棕眼、银甲蓝边、浅色兜帽尾与深色短裤严格沿用官方格兰身份锚点",
      "Traveller's Sword 完整入鞘并独立存在，不能变成册页、罗盘、封印或悬浮 UI"
    ],
    "forbidden": [
      "混入姬塔的金发、粉色头带、裙装或粉色装甲特征",
      "打开的格子册、十二个小圆槽、四个小方槽、专精罗盘、逐格插入动作、额外书册或超过四枚页签",
      "可读文字、数字、存档 UI、对话框、悬浮卡片或写入成功图标",
      "复制官方参考姿势、拔剑攻击、额外肢体或裁切手、册与武器"
    ]
  },
  "sticker": {
    "character": "gran",
    "selection_reason": "格兰的队长感适合承担覆盖前的最终确认提醒，让备份与目标槽核对显得可靠而不惊慌。",
    "voice": "稳重、简短、像队长在执行前做最后确认，不冒充官方台词。",
    "message": "先备份，再确认角色和目标槽；已有配装会被覆盖。",
    "emotion": "认真警醒",
    "gesture": "一手把唯一一本合上的备份账册抱在胸前，另一手捏住并检查书脊上的唯一实体封缄扣。",
    "prop": "一本合上的备份账册，以及固定在书脊封缄带上的一个实体扣。",
    "forbidden": [
      "画面内文字、数字、气泡或 UI",
      "多本账册、多个封印、额外肢体或模糊的悬浮确认动作",
      "庆祝、战斗攻击或与备份覆盖提醒无关的道具"
    ]
  }
}
